{
  "itemsSlider": [
    {"id": 1, "src": "30-1.jpg", "title": "HUD и спидометр"},
    {"id": 2, "src": "30-2.jpg", "title": "HUD и оружие"},
    {"id": 3, "src": "30-3.jpg", "title": "Диалоговые окна"},
    {"id": 4, "src": "30-4.jpg", "title": "Инвентарь"},
    {"id": 5, "src": "30-5.jpg", "title": "Киоски"},
    {"id": 7, "src": "30-7.jpg", "title": "Заправка"},
    {"id": 8, "src": "30-8.jpg", "title": "Радиальное меню"},
    {"id": 9, "src": "30-9.jpg", "title": "Информация о недвижимости + квест табло + текст на экране"},
    {"id": 10, "src": "30-10.jpg", "title": "Админспек"},
    {"id": 11, "src": "30-11.jpg", "title": "Репорт у админа (зетка)"},
    {"id": 12, "src": "30-12.jpg", "title": "Авторизация"},
    {"id": 13, "src": "30-13.jpg", "title": "Главное меню"},
    {"id": "g2", "src": "graphics-2.png", "title": "Warm Light [ENB]"},
    {"id": "g3", "src": "graphics-3.png", "title": "Blue Shade [ENB]"},
    {"id": "g4", "src": "graphics-4.png", "title": "Graphic Set [no ENB]"}
  ],
  "itemsPricing": [
    ["Кастомный <b>HUD</b>", 1, 1, "#slide-1"],
    ["Измененные <b>диалоговые окна</b>", 1, 1, "#slide-3"],
    ["Измененная <b>инвентарь</b>", 1, 1, "#slide-4"],
    ["Измененная <b>радиальное меню</b>", 1, 1, "#slide-8"],
    ["Измененная <b>киоск</b>", 1, 1, "#slide-5"],
    ["Измененная <b>заправка</b>", 1, 1, "#slide-7"],
    ["Измененные <b>admin spectate (/sp)</b>", 1, 1, "#slide-10"],
    ["Измененные остальные <b>интерфейсы</b>", 1, 1, "#jump-link-2"],
    ["<b>1</b> набор звуков оружия", 3, null, "/library?type=weapon-sounds&ids=lib17&sbID=30-3"],
    ["<b>Без</b> эффектов при попадании", 0, null, ""],
    ["<b>1</b> вариант прицела", 3, null, "/library?type=crosshairs&ids=lib13.3&sbID=30-3"],
    ["<b>Библиотека всех</b> звуков оружия", null, 1, "/library?type=weapon-sounds"],
    ["<b>Библиотека всех</b> эффектов при попадании", null, 1, "/library?type=hit-effects"],
    ["<b>Библиотека всех</b> прицелов", null, 1, "/library?type=crosshairs"],
    ["(Подарок) <b>4</b> вида графики", 2, 2, "#info-graphics__component-oneas"],
    ["(Подарок) Множество <b>плагинов</b>", 2, 2, "#info-plugins__component-oneas"]
  ],
  "descPricing": [
    "У вас есть возможность докупить комплектацию выше в любое время.",
    "После покупки вы получите все комплектации этой сборки."
  ],
  "infoDescPointsID": {
    "infoPlugins": [1, 2, 3, 4, 5, 7, 9, 10, 11, 12, 13, 14],
    "infoGraphics": [27, 28, 29]
  },
  "descriptionUrl": "description.html"
}